eventu/__init__.py
eventu/eventu.py
eventu/py.typed
eventu-0.1.3.dist-info/METADATA
eventu-0.1.3.dist-info/WHEEL
eventu-0.1.3.dist-info/RECORD
